AUTHORS
ChangeLog
LICENSE
MANIFEST.in
README.rst
requirements.txt
setup.cfg
setup.py
leonardo_module_forms/__init__.py
leonardo_module_forms/fields.py
leonardo_module_forms/models.py
leonardo_module_forms/settings.py
leonardo_module_forms/signals.py
leonardo_module_forms.egg-info/PKG-INFO
leonardo_module_forms.egg-info/SOURCES.txt
leonardo_module_forms.egg-info/dependency_links.txt
leonardo_module_forms.egg-info/not-zip-safe
leonardo_module_forms.egg-info/pbr.json
leonardo_module_forms.egg-info/requires.txt
leonardo_module_forms.egg-info/top_level.txt
leonardo_module_forms/locale/cs/LC_MESSAGES/django.po
leonardo_module_forms/templates/floppyforms/checkbox_select.html
leonardo_module_forms/templates/floppyforms/clearable_input.html
leonardo_module_forms/templates/floppyforms/input.html
leonardo_module_forms/templates/floppyforms/radio.html
leonardo_module_forms/templates/floppyforms/select.html
leonardo_module_forms/templates/floppyforms/textarea.html
leonardo_module_forms/templates/floppyforms/tinymce.html
leonardo_module_forms/templates/floppyforms/gis/google.html
leonardo_module_forms/templates/floppyforms/gis/openlayers.html
leonardo_module_forms/templates/floppyforms/gis/osm.html
leonardo_module_forms/templates/forms/button.html
leonardo_module_forms/templates/forms/errors.html
leonardo_module_forms/templates/forms/field.html
leonardo_module_forms/templates/forms/multifield.html
leonardo_module_forms/templates/forms/value.html
leonardo_module_forms/templates/widget/form/default.html
leonardo_module_forms/templates/widget/form/full.html
leonardo_module_forms/widget/__init__.py
leonardo_module_forms/widget/form/__init__.py
leonardo_module_forms/widget/form/forms.py
leonardo_module_forms/widget/form/models.py
leonardo_module_forms/widget/form/tables.py
requirements/recaptcha.txt
requirements/remote.txt